fava/__init__.py
fava/application.py
fava/cli.py
fava/context.py
fava/helpers.py
fava/internal_api.py
fava/json_api.py
fava/py.typed
fava/serialisation.py
fava/template_filters.py
fava/core/__init__.py
fava/core/_compat.py
fava/core/accounts.py
fava/core/attributes.py
fava/core/budgets.py
fava/core/charts.py
fava/core/commodities.py
fava/core/conversion.py
fava/core/documents.py
fava/core/entries_by_type.py
fava/core/extensions.py
fava/core/fava_options.py
fava/core/file.py
fava/core/filters.py
fava/core/ingest.py
fava/core/inventory.py
fava/core/misc.py
fava/core/module_base.py
fava/core/number.py
fava/core/query_shell.py
fava/core/tree.py
fava/core/watcher.py
fava/ext/__init__.py
fava/ext/auto_commit.py
fava/ext/portfolio_list/__init__.py
fava/ext/portfolio_list/templates/PortfolioList.html
fava/help/__init__.py
fava/help/_index.md
fava/help/beancount_syntax.md
fava/help/budgets.md
fava/help/extensions.md
fava/help/features.md
fava/help/filters.md
fava/help/import.md
fava/help/options.md
fava/plugins/__init__.py
fava/plugins/link_documents.py
fava/plugins/tag_discovered_documents.py
fava/static/.gitkeep
fava/static/app.css
fava/static/app.js
fava/static/fira-mono-all-400-normal-B3VA6PUD.woff
fava/static/fira-mono-all-500-normal-6H5PJVHM.woff
fava/static/fira-mono-cyrillic-400-normal-DHYMC6AA.woff2
fava/static/fira-mono-cyrillic-500-normal-GP3B6L2A.woff2
fava/static/fira-mono-cyrillic-ext-400-normal-47U2AFQV.woff2
fava/static/fira-mono-cyrillic-ext-500-normal-IYTP56HI.woff2
fava/static/fira-mono-greek-400-normal-TG32BQXP.woff2
fava/static/fira-mono-greek-500-normal-JKOMG4AV.woff2
fava/static/fira-mono-greek-ext-400-normal-5NS2LNAL.woff2
fava/static/fira-mono-greek-ext-500-normal-WGULELC2.woff2
fava/static/fira-mono-latin-400-normal-JUOXJG4X.woff2
fava/static/fira-mono-latin-500-normal-VF62XXV3.woff2
fava/static/fira-mono-latin-ext-400-normal-3XROC5NW.woff2
fava/static/fira-mono-latin-ext-500-normal-JGGLQGT6.woff2
fava/static/fira-sans-all-400-normal-Z3W4I7VT.woff
g8fyi_fava-1.0.5.dist-info/AUTHORS
g8fyi_fava-1.0.5.dist-info/LICENSE
g8fyi_fava-1.0.5.dist-info/METADATA
g8fyi_fava-1.0.5.dist-info/WHEEL
g8fyi_fava-1.0.5.dist-info/entry_points.txt
g8fyi_fava-1.0.5.dist-info/top_level.txt
g8fyi_fava-1.0.5.dist-info/RECORD
