Metadata-Version: 2.1
Name: g8fyi-fava
Version: 1.0.5
Summary: Web interface for the accounting tool Beancount.
Home-page: https://beancount.github.io/fava/
Author: Dominik Aumayr
Author-email: dominik@aumayr.name
Maintainer: Jay
Maintainer-email: admin@g8.fyi
License: MIT
Project-URL: Documentation, https://beancount.github.io/fava/
Project-URL: Changes, https://beancount.github.io/fava/changelog.html
Project-URL: Source Code, https://github.com/beancount/fava/
Project-URL: Issue Tracker, https://github.com/beancount/fava/issues/
Project-URL: Chat, https://gitter.im/beancount/fava
Keywords: fava beancount accounting
Classifier: Development Status :: 5 - Production/Stable
Classifier: Environment :: Web Environment
Classifier: Framework :: Flask
Classifier: Intended Audience :: Education
Classifier: Intended Audience :: End Users/Desktop
Classifier: Intended Audience :: Financial and Insurance Industry
Classifier: Intended Audience :: Information Technology
Classifier: License :: OSI Approved :: MIT License
Classifier: Natural Language :: English
Classifier: Programming Language :: JavaScript
Classifier: Programming Language :: Python :: 3 :: Only
Classifier: Programming Language :: Python :: 3.7
Classifier: Programming Language :: Python :: 3.8
Classifier: Programming Language :: Python :: 3.9
Classifier: Programming Language :: Python :: 3.10
Classifier: Programming Language :: Python :: 3.11
Classifier: Topic :: Internet :: WWW/HTTP :: Dynamic Content
Classifier: Topic :: Office/Business :: Financial :: Accounting
Classifier: Topic :: Office/Business :: Financial :: Investment
Requires-Python: >=3.7
License-File: LICENSE
License-File: AUTHORS
Requires-Dist: Babel (<3,>=2.7)
Requires-Dist: Flask-Babel (<4,>=1)
Requires-Dist: Flask (<3,>=2)
Requires-Dist: Jinja2 (<4,>=3)
Requires-Dist: Werkzeug (<3,>=2)
Requires-Dist: g8fyi-beancount (<3,>=1)
Requires-Dist: cheroot (<10,>=8)
Requires-Dist: click (<9,>=7)
Requires-Dist: markdown2 (<3,>=2.3.0)
Requires-Dist: ply
Requires-Dist: simplejson (<4,>=3.16.0)
Provides-Extra: excel
Requires-Dist: pyexcel (>=0.2.2) ; extra == 'excel'
Requires-Dist: pyexcel-ods3 (>=0.1.1) ; extra == 'excel'
Requires-Dist: pyexcel-xls (>=0.1.0) ; extra == 'excel'
Requires-Dist: pyexcel-xlsx (>=0.1.0) ; extra == 'excel'
